[
    {
        "auid": "000-BCQ-220",
        "ra": "22:15:03.51",
        "dec": "43:46:24.0",
        "label": "68",
        "bands": [
            {
                "band": "V",
                "mag": 6.822,
                "error": 0.1
            },
            {
                "band": "U",
                "mag": 8.827,
                "error": 0.15
            },
            {
                "band": "B",
                "mag": 7.916,
                "error": 0.1
            },
            {
                "band": "Rc",
                "mag": 6.232,
                "error": 0.15
            },
            {
                "band": "J",
                "mag": 5.131,
                "error": 0.286
            },
            {
                "band": "H",
                "mag": 4.488,
                "error": 0.214
            },
            {
                "band": "K",
                "mag": 4.173,
                "error": 8.888
            }
        ],
        "comments": "  "
    },
    {
        "auid": "000-BCQ-076",
        "ra": "22:11:09.64",
        "dec": "43:31:39.1",
        "label": "75",
        "bands": [
            {
                "band": "V",
                "mag": 7.513,
                "error": 0.074
            },
            {
                "band": "B",
                "mag": 8.698,
                "error": 0.082
            },
            {
                "band": "Ic",
                "mag": 6.275,
                "error": 0.225
            },
            {
                "band": "J",
                "mag": 5.372,
                "error": 0.019
            },
            {
                "band": "H",
                "mag": 4.849,
                "error": 0.019
            },
            {
                "band": "K",
                "mag": 4.707,
                "error": 0.013
            }
        ],
        "comments": ""
    },
    {
        "auid": "000-BCQ-229",
        "ra": "22:15:29.19",
        "dec": "43:44:53.4",
        "label": "76",
        "bands": [
            {
                "band": "V",
                "mag": 7.637,
                "error": 0.067
            },
            {
                "band": "B",
                "mag": 7.683,
                "error": 0.076
            },
            {
                "band": "Ic",
                "mag": 7.619,
                "error": 0.106
            },
            {
                "band": "J",
                "mag": 7.547,
                "error": 0.021
            },
            {
                "band": "H",
                "mag": 7.584,
                "error": 0.021
            },
            {
                "band": "K",
                "mag": 7.566,
                "error": 0.011
            }
        ],
        "comments": ""
    },
    {
        "auid": "000-BCQ-052",
        "ra": "22:10:11.68",
        "dec": "44:04:33.7",
        "label": "81",
        "bands": [
            {
                "band": "V",
                "mag": 8.096,
                "error": 0.074
            },
            {
                "band": "B",
                "mag": 9.024,
                "error": 0.082
            },
            {
                "band": "Ic",
                "mag": 7.127,
                "error": 0.116
            },
            {
                "band": "J",
                "mag": 6.354,
                "error": 0.009
            },
            {
                "band": "H",
                "mag": 5.881,
                "error": 0.019
            },
            {
                "band": "K",
                "mag": 5.83,
                "error": 0.019
            }
        ],
        "comments": ""
    },
    {
        "auid": "000-BCQ-209",
        "ra": "22:14:26.47",
        "dec": "43:39:43.1",
        "label": "81",
        "bands": [
            {
                "band": "V",
                "mag": 8.098,
                "error": 0.062
            },
            {
                "band": "B",
                "mag": 8.157,
                "error": 0.072
            },
            {
                "band": "Ic",
                "mag": 8.032,
                "error": 0.095
            },
            {
                "band": "J",
                "mag": 7.906,
                "error": 0.011
            },
            {
                "band": "H",
                "mag": 7.914,
                "error": 0.017
            },
            {
                "band": "K",
                "mag": 7.887,
                "error": 0.025
            }
        ],
        "comments": ""
    },
    {
        "auid": "000-BCQ-098",
        "ra": "22:11:33.24",
        "dec": "43:27:44.7",
        "label": "95",
        "bands": [
            {
                "band": "V",
                "mag": 9.51,
                "error": 0.035
            },
            {
                "band": "B",
                "mag": 9.99,
                "error": 0.054
            },
            {
                "band": "Ic",
                "mag": 8.969,
                "error": 0.107
            },
            {
                "band": "J",
                "mag": 8.558,
                "error": 0.017
            },
            {
                "band": "H",
                "mag": 8.42,
                "error": 0.032
            },
            {
                "band": "K",
                "mag": 8.345,
                "error": 0.019
            }
        ],
        "comments": ""
    },
    {
        "auid": "000-BCQ-055",
        "ra": "22:10:21.20",
        "dec": "43:51:34.6",
        "label": "99",
        "bands": [
            {
                "band": "V",
                "mag": 9.853,
                "error": 0.038
            },
            {
                "band": "B",
                "mag": 10.253,
                "error": 0.059
            },
            {
                "band": "Ic",
                "mag": 9.516,
                "error": 0.098
            },
            {
                "band": "J",
                "mag": 9.182,
                "error": 0.02
            },
            {
                "band": "H",
                "mag": 9.049,
                "error": 0.027
            },
            {
                "band": "K",
                "mag": 9.019,
                "error": 0.02
            }
        ],
        "comments": ""
    },
    {
        "auid": "000-BCQ-115",
        "ra": "22:11:45.63",
        "dec": "43:46:13.7",
        "label": "100",
        "bands": [
            {
                "band": "V",
                "mag": 9.972,
                "error": 0.039
            },
            {
                "band": "B",
                "mag": 10.524,
                "error": 0.063
            },
            {
                "band": "J",
                "mag": 8.848,
                "error": 0.007
            },
            {
                "band": "H",
                "mag": 8.552,
                "error": 0.027
            },
            {
                "band": "K",
                "mag": 8.498,
                "error": 0.019
            }
        ],
        "comments": ""
    },
    {
        "auid": "000-BKP-740",
        "ra": "22:15:35.55",
        "dec": "43:52:15.2",
        "label": "104",
        "bands": [
            {
                "band": "V",
                "mag": 10.358,
                "error": 0.03
            },
            {
                "band": "B",
                "mag": 10.928,
                "error": 0.08
            },
            {
                "band": "Rc",
                "mag": 9.923,
                "error": 0.03
            },
            {
                "band": "Ic",
                "mag": 9.516,
                "error": 0.03
            }
        ],
        "comments": null
    },
    {
        "auid": "000-BLF-906",
        "ra": "22:10:03.74",
        "dec": "43:54:21.8",
        "label": "104",
        "bands": [
            {
                "band": "V",
                "mag": 10.45,
                "error": 0.028
            },
            {
                "band": "B",
                "mag": 10.948,
                "error": 0.041
            },
            {
                "band": "Rc",
                "mag": 10.104,
                "error": 0.042
            },
            {
                "band": "Ic",
                "mag": 9.778,
                "error": 0.052
            }
        ],
        "comments": null
    },
    {
        "auid": "000-BLF-907",
        "ra": "22:12:42.18",
        "dec": "44:08:14.1",
        "label": "106",
        "bands": [
            {
                "band": "V",
                "mag": 10.578,
                "error": 0.025
            },
            {
                "band": "B",
                "mag": 11.055,
                "error": 0.063
            },
            {
                "band": "Rc",
                "mag": 10.213,
                "error": 0.025
            },
            {
                "band": "Ic",
                "mag": 9.87,
                "error": 0.025
            }
        ],
        "comments": null
    },
    {
        "auid": "000-BLF-908",
        "ra": "22:11:48.23",
        "dec": "43:32:14.4",
        "label": "108",
        "bands": [
            {
                "band": "V",
                "mag": 10.802,
                "error": 0.091
            },
            {
                "band": "B",
                "mag": 11.271,
                "error": 0.151
            },
            {
                "band": "Rc",
                "mag": 10.383,
                "error": 0.091
            },
            {
                "band": "Ic",
                "mag": 9.99,
                "error": 0.091
            }
        ],
        "comments": null
    },
    {
        "auid": "000-BLF-909",
        "ra": "22:10:00.14",
        "dec": "43:41:04.2",
        "label": "110",
        "bands": [
            {
                "band": "V",
                "mag": 11.01,
                "error": 0.092
            },
            {
                "band": "B",
                "mag": 11.657,
                "error": 0.141
            },
            {
                "band": "Rc",
                "mag": 10.58,
                "error": 0.101
            },
            {
                "band": "Ic",
                "mag": 10.178,
                "error": 0.109
            }
        ],
        "comments": null
    },
    {
        "auid": "000-BLF-910",
        "ra": "22:11:33.99",
        "dec": "43:41:56.0",
        "label": "113",
        "bands": [
            {
                "band": "V",
                "mag": 11.348,
                "error": 0.073
            },
            {
                "band": "B",
                "mag": 11.767,
                "error": 0.135
            },
            {
                "band": "Rc",
                "mag": 11.005,
                "error": 0.073
            },
            {
                "band": "Ic",
                "mag": 10.682,
                "error": 0.073
            }
        ],
        "comments": null
    },
    {
        "auid": "000-BCQ-146",
        "ra": "22:12:32.52",
        "dec": "43:48:30.5",
        "label": "116",
        "bands": [
            {
                "band": "V",
                "mag": 11.556,
                "error": 0.067
            },
            {
                "band": "B",
                "mag": 12.168,
                "error": 0.13
            },
            {
                "band": "Rc",
                "mag": 11.126,
                "error": 0.067
            },
            {
                "band": "Ic",
                "mag": 10.723,
                "error": 0.067
            },
            {
                "band": "J",
                "mag": 10.23,
                "error": 0.018
            },
            {
                "band": "H",
                "mag": 9.965,
                "error": 0.019
            },
            {
                "band": "K",
                "mag": 9.901,
                "error": 0.013
            }
        ],
        "comments": ""
    },
    {
        "auid": "000-BKP-741",
        "ra": "22:15:40.67",
        "dec": "44:01:09.0",
        "label": "117",
        "bands": [
            {
                "band": "V",
                "mag": 11.688,
                "error": 0.008
            },
            {
                "band": "B",
                "mag": 12.363,
                "error": 0.079
            },
            {
                "band": "Rc",
                "mag": 11.256,
                "error": 0.008
            },
            {
                "band": "Ic",
                "mag": 10.851,
                "error": 0.008
            }
        ],
        "comments": null
    },
    {
        "auid": "000-BLF-911",
        "ra": "22:13:16.19",
        "dec": "43:57:28.4",
        "label": "119",
        "bands": [
            {
                "band": "V",
                "mag": 11.897,
                "error": 0.041
            },
            {
                "band": "B",
                "mag": 12.533,
                "error": 0.098
            },
            {
                "band": "Rc",
                "mag": 11.389,
                "error": 0.041
            },
            {
                "band": "Ic",
                "mag": 10.915,
                "error": 0.041
            }
        ],
        "comments": null
    },
    {
        "auid": "000-BKP-742",
        "ra": "22:14:31.32",
        "dec": "43:58:29.7",
        "label": "121",
        "bands": [
            {
                "band": "V",
                "mag": 12.125,
                "error": 0.023
            },
            {
                "band": "B",
                "mag": 12.628,
                "error": 0.087
            },
            {
                "band": "Rc",
                "mag": 11.764,
                "error": 0.023
            },
            {
                "band": "Ic",
                "mag": 11.425,
                "error": 0.023
            }
        ],
        "comments": null
    },
    {
        "auid": "000-BLF-912",
        "ra": "22:12:23.39",
        "dec": "43:36:13.2",
        "label": "121",
        "bands": [
            {
                "band": "V",
                "mag": 12.104,
                "error": 0.108
            },
            {
                "band": "B",
                "mag": 12.694,
                "error": 0.182
            },
            {
                "band": "Rc",
                "mag": 11.656,
                "error": 0.108
            },
            {
                "band": "Ic",
                "mag": 11.237,
                "error": 0.108
            }
        ],
        "comments": null
    },
    {
        "auid": "000-BLF-913",
        "ra": "22:11:43.00",
        "dec": "43:47:41.8",
        "label": "122",
        "bands": [
            {
                "band": "V",
                "mag": 12.153,
                "error": 0.086
            },
            {
                "band": "B",
                "mag": 12.756,
                "error": 0.153
            },
            {
                "band": "Rc",
                "mag": 11.729,
                "error": 0.086
            },
            {
                "band": "Ic",
                "mag": 11.332,
                "error": 0.086
            }
        ],
        "comments": null
    },
    {
        "auid": "000-BCQ-161",
        "ra": "22:13:03.82",
        "dec": "43:44:49.4",
        "label": "124",
        "bands": [
            {
                "band": "V",
                "mag": 12.431,
                "error": 0.082
            },
            {
                "band": "B",
                "mag": 12.974,
                "error": 0.145
            },
            {
                "band": "Rc",
                "mag": 12.029,
                "error": 0.082
            },
            {
                "band": "Ic",
                "mag": 11.652,
                "error": 0.082
            },
            {
                "band": "J",
                "mag": 11.186,
                "error": 0.02
            },
            {
                "band": "H",
                "mag": 10.915,
                "error": 0.019
            },
            {
                "band": "K",
                "mag": 10.882,
                "error": 0.013
            }
        ],
        "comments": ""
    },
    {
        "auid": "000-BLF-914",
        "ra": "22:14:04.44",
        "dec": "43:41:21.0",
        "label": "126",
        "bands": [
            {
                "band": "V",
                "mag": 12.592,
                "error": 0.057
            },
            {
                "band": "B",
                "mag": 13.249,
                "error": 0.124
            },
            {
                "band": "Rc",
                "mag": 12.176,
                "error": 0.057
            },
            {
                "band": "Ic",
                "mag": 11.786,
                "error": 0.057
            }
        ],
        "comments": null
    },
    {
        "auid": "000-BKP-743",
        "ra": "22:14:58.12",
        "dec": "44:11:42.9",
        "label": "127",
        "bands": [
            {
                "band": "V",
                "mag": 12.697,
                "error": 0.008
            },
            {
                "band": "B",
                "mag": 13.251,
                "error": 0.061
            },
            {
                "band": "Rc",
                "mag": 12.249,
                "error": 0.022
            },
            {
                "band": "Ic",
                "mag": 11.829,
                "error": 0.031
            }
        ],
        "comments": null
    },
    {
        "auid": "000-BKP-744",
        "ra": "22:14:33.81",
        "dec": "44:01:20.9",
        "label": "131",
        "bands": [
            {
                "band": "V",
                "mag": 13.055,
                "error": 0.026
            },
            {
                "band": "B",
                "mag": 13.858,
                "error": 0.089
            },
            {
                "band": "Rc",
                "mag": 12.455,
                "error": 0.026
            },
            {
                "band": "Ic",
                "mag": 11.896,
                "error": 0.026
            }
        ],
        "comments": null
    },
    {
        "auid": "000-BCQ-136",
        "ra": "22:12:18.61",
        "dec": "43:48:52.7",
        "label": "132",
        "bands": [
            {
                "band": "V",
                "mag": 13.217,
                "error": 0.133
            },
            {
                "band": "B",
                "mag": 13.832,
                "error": 0.207
            },
            {
                "band": "Rc",
                "mag": 12.742,
                "error": 0.133
            },
            {
                "band": "Ic",
                "mag": 12.298,
                "error": 0.133
            },
            {
                "band": "J",
                "mag": 11.666,
                "error": 0.016
            },
            {
                "band": "H",
                "mag": 11.377,
                "error": 0.019
            },
            {
                "band": "K",
                "mag": 11.303,
                "error": 0.013
            }
        ],
        "comments": ""
    },
    {
        "auid": "000-BKP-745",
        "ra": "22:14:42.65",
        "dec": "44:04:59.3",
        "label": "140",
        "bands": [
            {
                "band": "V",
                "mag": 14.007,
                "error": 0.059
            },
            {
                "band": "B",
                "mag": 14.833,
                "error": 0.116
            },
            {
                "band": "Rc",
                "mag": 13.371,
                "error": 0.059
            },
            {
                "band": "Ic",
                "mag": 12.779,
                "error": 0.059
            }
        ],
        "comments": null
    },
    {
        "auid": "000-BKP-746",
        "ra": "22:16:17.54",
        "dec": "44:03:47.5",
        "label": "143",
        "bands": [
            {
                "band": "V",
                "mag": 14.318,
                "error": 0.066
            },
            {
                "band": "B",
                "mag": 15.081,
                "error": 0.127
            },
            {
                "band": "Rc",
                "mag": 13.816,
                "error": 0.066
            },
            {
                "band": "Ic",
                "mag": 13.348,
                "error": 0.066
            }
        ],
        "comments": null
    },
    {
        "auid": "000-BKP-747",
        "ra": "22:15:36.40",
        "dec": "44:06:37.8",
        "label": "149",
        "bands": [
            {
                "band": "V",
                "mag": 14.943,
                "error": 0.012
            },
            {
                "band": "B",
                "mag": 15.821,
                "error": 0.156
            },
            {
                "band": "Rc",
                "mag": 14.37,
                "error": 0.012
            },
            {
                "band": "Ic",
                "mag": 13.836,
                "error": 0.012
            }
        ],
        "comments": null
    }
]